quickscope/__init__.py
quickscope/__main__.py
quickscope/common.py
quickscope/shooter.py
quickscope/statuspage.py
quickscope/tracker.py
tests/__init__.py
tests/script_basic.py
tests/test.py
tests/test_ignore.py
quickscope-0.1.7.dist-info/METADATA
quickscope-0.1.7.dist-info/WHEEL
quickscope-0.1.7.dist-info/entry_points.txt
quickscope-0.1.7.dist-info/top_level.txt
quickscope-0.1.7.dist-info/RECORD
