Metadata-Version: 2.1
Name: quickscope
Version: 0.1.7
Summary: A lightweight and scalable A/D CTF exploit shooter
Home-page: https://github.com/shellphish/quickscope
License: zlib
Requires-Python: >=3.8
Requires-Dist: nclib >=1.0.3
Requires-Dist: psutil
Requires-Dist: dataclasses-json
Requires-Dist: ipython
Requires-Dist: readerwriterlock
